scholarly_infrastructure/__init__.py
scholarly_infrastructure/_modidx.py
scholarly_infrastructure/fun_star.py
scholarly_infrastructure/help.py
scholarly_infrastructure/logging.py
scholarly_infrastructure/nucleus.py
scholarly_infrastructure/rv_args.py
scholarly_infrastructure/logging/__init__.py
scholarly_infrastructure/logging/infra.py
scholarly_infrastructure/logging/nucleus.py
scholarly_infrastructure/logging/torch.py
scholarly_infrastructure/rv_args/__init__.py
scholarly_infrastructure/rv_args/fun_star.py
scholarly_infrastructure/rv_args/nucleus.py
ScholarlyInfrastructure-0.0.2.dist-info/LICENSE
ScholarlyInfrastructure-0.0.2.dist-info/METADATA
ScholarlyInfrastructure-0.0.2.dist-info/WHEEL
ScholarlyInfrastructure-0.0.2.dist-info/entry_points.txt
ScholarlyInfrastructure-0.0.2.dist-info/top_level.txt
ScholarlyInfrastructure-0.0.2.dist-info/RECORD
