Metadata-Version: 2.1
Name: ScholarlyInfrastructure
Version: 0.0.2
Summary: 所谓大学者，非谓有大楼之谓也，有大师之谓也。
Home-page: https://github.com/THU-CVML/ScholarlyInfrastructure
Author: 叶璨铭 (Ye Canming)
Author-email: ycm24@mails.tsinghua.edu.cn
License: Apache Software License 2.0
Keywords: nbdev jupyter notebook python thu tsinghua cv ml vision learning
Classifier: Development Status :: 4 - Beta
Classifier: Intended Audience :: Developers
Classifier: Natural Language :: English
Classifier: Programming Language :: Python :: 3.7
Classifier: Programming Language :: Python :: 3.8
Classifier: Programming Language :: Python :: 3.9
Classifier: Programming Language :: Python :: 3.10
Classifier: Programming Language :: Python :: 3.11
Classifier: Programming Language :: Python :: 3.12
Classifier: License :: OSI Approved :: Apache Software License
Requires-Python: >=3.7
License-File: LICENSE
Requires-Dist: fastcore
Requires-Dist: decorator
Requires-Dist: pydantic
Requires-Dist: loguru
Requires-Dist: bigmodelvis
Requires-Dist: richuru
Requires-Dist: optuna
Provides-Extra: dev
Requires-Dist: nbdev; extra == "dev"
Requires-Dist: ipykernel; extra == "dev"
